[
    {
        "id": "SEE001",
        "feature": "see_cli_legacy",
        "helpers": "",
        "description": "Generate a Help message legacy cli commands. (see_cli_legacy)",
        "command": "see_cli_legacy",
        "options": "see_cli_legacy",
        "status": "review",
        "condition": " ",
        "reference": "",
        "author": "@Tearran",
        "group": "",
        "commands": "",
        "port": "",
        "arch": ""
    },
    {
        "id": "SET002",
        "feature": "set_runtime_variables",
        "helpers": "",
        "description": "Run time variables Migrated procedures from Armbian config. (set_runtime_variables)",
        "command": "set_runtime_variables",
        "options": "set_runtime_variables",
        "status": "Active",
        "condition": " ",
        "reference": "",
        "author": "@igorpecovnik",
        "group": "",
        "commands": "",
        "port": "",
        "arch": ""
    },
    {
        "id": "SET003",
        "feature": "set_interface",
        "helpers": "",
        "description": "Check for (Whiptail, DIALOG, READ) tools and set the user interface. (set_interface)",
        "command": "set_interface",
        "options": "",
        "status": "review",
        "condition": " ",
        "reference": "",
        "author": "Tearran",
        "group": "",
        "commands": "",
        "port": "",
        "arch": ""
    },
    {
        "id": "TOG004",
        "feature": "toggle_ssh_lastlog",
        "helpers": "",
        "description": "Toggle SSH lastlog (toggle_ssh_lastlog)",
        "command": "toggle_ssh_lastlog",
        "options": "toggle_ssh_lastlog",
        "status": "Active",
        "condition": " ",
        "reference": "",
        "author": "@Tearran",
        "group": "",
        "commands": "",
        "port": "",
        "arch": ""
    },
    {
        "id": "SEE005",
        "feature": "see_function_table_md",
        "helpers": "",
        "description": "Generate this markdown table of all module_options (see_function_table_md)",
        "command": "see_function_table_md",
        "options": "see_function_table_md",
        "status": "review",
        "condition": " ",
        "reference": "",
        "author": "@Tearran",
        "group": "",
        "commands": "",
        "port": "",
        "arch": ""
    },
    {
        "id": "MOD006",
        "feature": "module_webmin",
        "helpers": "",
        "description": "Webmin setup and service setting. (module_webmin)",
        "command": "module_webmin",
        "options": "help install remove start stop enable disable status check",
        "status": "review",
        "condition": " ",
        "reference": "",
        "author": "@Tearran",
        "group": "",
        "commands": "",
        "port": "",
        "arch": ""
    },
    {
        "id": "MOD007",
        "feature": "module_haos",
        "helpers": "",
        "description": "Install HA supervised container (module_haos)",
        "command": "module_haos",
        "options": "install remove purge status help",
        "status": "Active",
        "condition": " ",
        "reference": "",
        "author": "@igorpecovnik",
        "group": "HomeAutomation",
        "commands": "",
        "port": "8123",
        "arch": "x86-64 arm64 armhf"
    },
    {
        "id": "MAN008",
        "feature": "manage_overlayfs",
        "helpers": "",
        "description": "Set Armbian root filesystem to read only (manage_overlayfs)",
        "command": "manage_overlayfs",
        "options": "manage_overlayfs enable/disable",
        "status": "Active",
        "condition": " ",
        "reference": "",
        "author": "@igorpecovnik",
        "group": "",
        "commands": "",
        "port": "",
        "arch": ""
    },
    {
        "id": "SHO009",
        "feature": "show_menu",
        "helpers": "",
        "description": "Display a menu from pipe (show_menu)",
        "command": "show_menu",
        "options": "show_menu <<< armbianmonitor -h  ; ",
        "status": "Active",
        "condition": " ",
        "reference": "",
        "author": "@Tearran",
        "group": "",
        "commands": "",
        "port": "",
        "arch": ""
    },
    {
        "id": "MOD010",
        "feature": "module_watchtower",
        "helpers": "",
        "description": "Install watchtower container (module_watchtower)",
        "command": "module_watchtower",
        "options": "install remove status help",
        "status": "Active",
        "condition": " ",
        "reference": "",
        "author": "@armbian",
        "group": "",
        "commands": "",
        "port": "",
        "arch": ""
    },
    {
        "id": "GEN011",
        "feature": "generate_top_menu",
        "helpers": "",
        "description": "Build the main menu from a object (generate_top_menu)",
        "command": "generate_top_menu",
        "options": "generate_top_menu 'json_data'",
        "status": "Active",
        "condition": " ",
        "reference": "",
        "author": "@Tearran",
        "group": "",
        "commands": "",
        "port": "",
        "arch": ""
    },
    {
        "id": "MOD012",
        "feature": "module_bazarr",
        "helpers": "",
        "description": "Install bazarr container (module_bazarr)",
        "command": "module_bazarr",
        "options": "install remove purge status help",
        "status": "Active",
        "condition": " ",
        "reference": "",
        "author": "",
        "group": "Downloaders",
        "commands": "",
        "port": "6767",
        "arch": "x86-64 arm64"
    },
    {
        "id": "MOD013",
        "feature": "module_headers",
        "helpers": "",
        "description": "Install headers container (module_headers)",
        "command": "module_headers",
        "options": "install remove status help",
        "status": "Active",
        "condition": " ",
        "reference": "",
        "author": "@armbian",
        "group": "",
        "commands": "",
        "port": "",
        "arch": ""
    },
    {
        "id": "IS_014",
        "feature": "is_package_manager_running",
        "helpers": "",
        "description": "Migrated procedures from Armbian config. (is_package_manager_running)",
        "command": "is_package_manager_running",
        "options": "is_package_manager_running",
        "status": "Active",
        "condition": " ",
        "reference": "",
        "author": "@armbian",
        "group": "",
        "commands": "",
        "port": "",
        "arch": ""
    },
    {
        "id": "CHE015",
        "feature": "check_desktop",
        "helpers": "",
        "description": "Migrated procedures from Armbian config. (check_desktop)",
        "command": "check_desktop",
        "options": "check_desktop",
        "status": "Active",
        "condition": " ",
        "reference": "",
        "author": "@armbian",
        "group": "",
        "commands": "",
        "port": "",
        "arch": ""
    },
    {
        "id": "MOD016",
        "feature": "module_phpmyadmin",
        "helpers": "",
        "description": "Install phpmyadmin container (module_phpmyadmin)",
        "command": "module_phpmyadmin",
        "options": "install remove purge status help",
        "status": "Active",
        "condition": " ",
        "reference": "",
        "author": "",
        "group": "",
        "commands": "",
        "port": "8071",
        "arch": ""
    },
    {
        "id": "MOD017",
        "feature": "module_stirling",
        "helpers": "",
        "description": "Install stirling container (module_stirling)",
        "command": "module_stirling",
        "options": "install remove purge status help",
        "status": "Active",
        "condition": " ",
        "reference": "",
        "author": "@Frooodle",
        "group": "",
        "commands": "",
        "port": "8077",
        "arch": ""
    },
    {
        "id": "MOD018",
        "feature": "module_sonarr",
        "helpers": "",
        "description": "Install sonarr container (module_sonarr)",
        "command": "module_sonarr",
        "options": "install remove purge status help",
        "status": "Active",
        "condition": " ",
        "reference": "",
        "author": "@armbian",
        "group": "Downloaders",
        "commands": "",
        "port": "8989",
        "arch": "x86-64 arm64"
    },
    {
        "id": "GEN019",
        "feature": "generate_readme",
        "helpers": "",
        "description": "Generate Document files. (generate_readme)",
        "command": "generate_readme",
        "options": "generate_readme",
        "status": "review",
        "condition": " ",
        "reference": "",
        "author": "@Tearran",
        "group": "",
        "commands": "",
        "port": "",
        "arch": ""
    },
    {
        "id": "STO020",
        "feature": "store_netplan_config",
        "helpers": "",
        "description": "Storing netplan config to tmp (store_netplan_config)",
        "command": "store_netplan_config",
        "options": "store_netplan_config",
        "status": "Active",
        "condition": " ",
        "reference": "store_netplan_config",
        "author": "@igorpecovnik",
        "group": "",
        "commands": "",
        "port": "",
        "arch": ""
    },
    {
        "id": "MOD021",
        "feature": "module_jellyseerr",
        "helpers": "",
        "description": "Install jellyseerr container (module_jellyseerr)",
        "command": "module_jellyseerr",
        "options": "install remove purge status help",
        "status": "Active",
        "condition": " ",
        "reference": "",
        "author": "@armbian",
        "group": "",
        "commands": "",
        "port": "5055",
        "arch": "x86-64,arm64"
    },
    {
        "id": "EXE022",
        "feature": "execute_command",
        "helpers": "",
        "description": "Needed by generate_menu (execute_command)",
        "command": "execute_command",
        "options": "execute_command 'id'",
        "status": "Active",
        "condition": " ",
        "reference": "",
        "author": "@Tearran",
        "group": "",
        "commands": "",
        "port": "",
        "arch": ""
    },
    {
        "id": "GET023",
        "feature": "get_user_continue",
        "helpers": "",
        "description": "Display a Yes/No dialog box and process continue/exit (get_user_continue)",
        "command": "get_user_continue",
        "options": "get_user_continue 'Do you wish to continue?' process_input",
        "status": "Active",
        "condition": " ",
        "reference": "",
        "author": "@Tearran",
        "group": "",
        "commands": "",
        "port": "",
        "arch": ""
    },
    {
        "id": "MOD024",
        "feature": "module_armbian_firmware",
        "helpers": "",
        "description": "Module for Armbian firmware manipulating. (module_armbian_firmware)",
        "command": "module_armbian_firmware",
        "options": "select install show hold unhold repository headers help",
        "status": "review",
        "condition": " ",
        "reference": "",
        "author": "@igorpecovnik",
        "group": "",
        "commands": "",
        "port": "",
        "arch": ""
    },
    {
        "id": "CON025",
        "feature": "connect_bt_interface",
        "helpers": "",
        "description": "Migrated procedures from Armbian config. (connect_bt_interface)",
        "command": "connect_bt_interface",
        "options": "connect_bt_interface",
        "status": "Active",
        "condition": " ",
        "reference": "",
        "author": "@armbian",
        "group": "",
        "commands": "",
        "port": "",
        "arch": ""
    },
    {
        "id": "SHO026",
        "feature": "show_message",
        "helpers": "",
        "description": "Display a message box (show_message)",
        "command": "show_message",
        "options": "show_message <<< 'hello world' ",
        "status": "Active",
        "condition": " ",
        "reference": "",
        "author": "@Tearran",
        "group": "",
        "commands": "",
        "port": "",
        "arch": ""
    },
    {
        "id": "SEE027",
        "feature": "see_monitoring",
        "helpers": "",
        "description": "Menu for armbianmonitor features (see_monitoring)",
        "command": "see_monitoring",
        "options": "see_monitoring",
        "status": "review",
        "condition": " ",
        "reference": "",
        "author": "@Tearran",
        "group": "",
        "commands": "",
        "port": "",
        "arch": ""
    },
    {
        "id": "MAN028",
        "feature": "manage_dtoverlays",
        "helpers": "",
        "description": "Enable/disable device tree overlays (manage_dtoverlays)",
        "command": "manage_dtoverlays",
        "options": "manage_dtoverlays",
        "status": "Active",
        "condition": " ",
        "reference": "",
        "author": "@viraniac",
        "group": "",
        "commands": "",
        "port": "",
        "arch": ""
    },
    {
        "id": "QR_029",
        "feature": "qr_code",
        "helpers": "",
        "description": "Show or generate QR code for Google OTP (qr_code)",
        "command": "qr_code",
        "options": "qr_code generate",
        "status": "Active",
        "condition": " ",
        "reference": "",
        "author": "@igorpecovnik",
        "group": "",
        "commands": "",
        "port": "",
        "arch": ""
    },
    {
        "id": "PI_030",
        "feature": "pi_hole",
        "helpers": "",
        "description": "Install/uninstall/check status of pi-hole container (pi_hole)",
        "command": "pi_hole",
        "options": "help install uninstall status password",
        "status": "Active",
        "condition": " ",
        "reference": "",
        "author": "@armbian",
        "group": "",
        "commands": "",
        "port": "",
        "arch": ""
    },
    {
        "id": "PKG031",
        "feature": "pkg_remove",
        "helpers": "",
        "description": "Remove package (pkg_remove)",
        "command": "pkg_remove",
        "options": "pkg_remove nmap",
        "status": "Interface",
        "condition": " ",
        "reference": "",
        "author": "@dimitry-ishenko",
        "group": "",
        "commands": "",
        "port": "",
        "arch": ""
    },
    {
        "id": "SEE032",
        "feature": "see_current_apt",
        "helpers": "",
        "description": "Check when apt list was last updated and suggest updating or update (see_current_apt)",
        "command": "see_current_apt",
        "options": "see_current_apt or see_current_apt update",
        "status": "Active",
        "condition": " ",
        "reference": "",
        "author": "@Tearran",
        "group": "",
        "commands": "",
        "port": "",
        "arch": ""
    },
    {
        "id": "MOD033",
        "feature": "module_portainer",
        "helpers": "",
        "description": "Install/uninstall/check status of portainer container (module_portainer)",
        "command": "module_portainer",
        "options": "help install uninstall status",
        "status": "Active",
        "condition": " ",
        "reference": "",
        "author": "@armbian",
        "group": "",
        "commands": "",
        "port": "9000",
        "arch": ""
    },
    {
        "id": "GEN034",
        "feature": "generate_svg",
        "helpers": "",
        "description": "Generate 'Armbian CPU logo' SVG for document file. (generate_svg)",
        "command": "generate_svg",
        "options": "generate_svg",
        "status": "review",
        "condition": " ",
        "reference": "",
        "author": "@Tearran",
        "group": "",
        "commands": "",
        "port": "",
        "arch": ""
    },
    {
        "id": "PKG035",
        "feature": "pkg_full_upgrade",
        "helpers": "",
        "description": "Upgrade installed packages (potentially removing some) (pkg_full_upgrade)",
        "command": "pkg_full_upgrade",
        "options": "pkg_full_upgrade",
        "status": "Interface",
        "condition": " ",
        "reference": "",
        "author": "@dimitry-ishenko",
        "group": "",
        "commands": "",
        "port": "",
        "arch": ""
    },
    {
        "id": "MOD036",
        "feature": "module_zfs",
        "helpers": "",
        "description": "Install zfs filesystem support (module_zfs)",
        "command": "module_zfs",
        "options": "install remove status kernel_max zfs_version zfs_installed_version help",
        "status": "Active",
        "condition": " ",
        "reference": "",
        "author": "@igorpecovnik",
        "group": "",
        "commands": "",
        "port": "",
        "arch": ""
    },
    {
        "id": "PKG037",
        "feature": "pkg_installed",
        "helpers": "",
        "description": "Check if package is installed (pkg_installed)",
        "command": "pkg_installed",
        "options": "pkg_installed mc",
        "status": "Interface",
        "condition": " ",
        "reference": "",
        "author": "@dimitry-ishenko",
        "group": "",
        "commands": "",
        "port": "",
        "arch": ""
    },
    {
        "id": "UPD038",
        "feature": "update_submenu_data",
        "helpers": "",
        "description": "Update submenu descriptions based on conditions (update_submenu_data)",
        "command": "update_submenu_data",
        "options": "update_submenu_data",
        "status": "review",
        "condition": " ",
        "reference": "",
        "author": "@Tearran",
        "group": "",
        "commands": "",
        "port": "",
        "arch": ""
    },
    {
        "id": "SAN039",
        "feature": "sanitize_input",
        "helpers": "",
        "description": "sanitize input cli (sanitize_input)",
        "command": "sanitize_input",
        "options": "sanitize_input",
        "status": "Review",
        "condition": " ",
        "reference": "",
        "author": "@Tearran",
        "group": "",
        "commands": "",
        "port": "",
        "arch": ""
    },
    {
        "id": "PKG040",
        "feature": "pkg_upgrade",
        "helpers": "",
        "description": "Upgrade installed packages (pkg_upgrade)",
        "command": "pkg_upgrade",
        "options": "pkg_upgrade",
        "status": "Interface",
        "condition": " ",
        "reference": "",
        "author": "@dimitry-ishenko",
        "group": "",
        "commands": "",
        "port": "",
        "arch": ""
    },
    {
        "id": "MOD041",
        "feature": "module_lidarr",
        "helpers": "",
        "description": "Install lidarr container (module_lidarr)",
        "command": "module_lidarr",
        "options": "install remove purge status help",
        "status": "Active",
        "condition": " ",
        "reference": "",
        "author": "@armbian",
        "group": "Downloaders",
        "commands": "",
        "port": "8686",
        "arch": "x86-64 arm64"
    },
    {
        "id": "CHE042",
        "feature": "check_ip_version",
        "helpers": "",
        "description": "Check if a domain is reachable via IPv4 and IPv6 (check_ip_version)",
        "command": "check_ip_version",
        "options": "check_ip_version google.com",
        "status": "review",
        "condition": " ",
        "reference": "",
        "author": "@Tearran",
        "group": "",
        "commands": "",
        "port": "",
        "arch": ""
    },
    {
        "id": "PKG043",
        "feature": "pkg_install",
        "helpers": "",
        "description": "Install package (pkg_install)",
        "command": "pkg_install",
        "options": "pkg_install neovim",
        "status": "Interface",
        "condition": " ",
        "reference": "",
        "author": "@dimitry-ishenko",
        "group": "",
        "commands": "",
        "port": "",
        "arch": ""
    },
    {
        "id": "MOD044",
        "feature": "module_swag",
        "helpers": "",
        "description": "Secure Web Application Gateway  (module_swag)",
        "command": "module_swag",
        "options": "install remove purge status password help",
        "status": "Active",
        "condition": " ",
        "reference": "",
        "author": "@igorpecovnik",
        "group": "WebHosting",
        "commands": "",
        "port": "443",
        "arch": "x86-64 arm64"
    },
    {
        "id": "MOD045",
        "feature": "module_deluge",
        "helpers": "",
        "description": "Install deluge container (module_deluge)",
        "command": "module_deluge",
        "options": "install remove purge status help",
        "status": "Active",
        "condition": " ",
        "reference": "",
        "author": "@igorpecovnik",
        "group": "Downloaders",
        "commands": "",
        "port": "8112 6181 58846",
        "arch": "x86-64 arm64"
    },
    {
        "id": "GEN046",
        "feature": "generate_menu",
        "helpers": "",
        "description": "Generate a submenu from a parent_id (generate_menu)",
        "command": "generate_menu",
        "options": "generate_menu 'parent_id'",
        "status": "Active",
        "condition": " ",
        "reference": "",
        "author": "@Tearran",
        "group": "",
        "commands": "",
        "port": "",
        "arch": ""
    },
    {
        "id": "SEE047",
        "feature": "see_jq_menu_list",
        "helpers": "",
        "description": "Generate a markdown list json objects using jq. (see_jq_menu_list)",
        "command": "see_jq_menu_list",
        "options": "see_jq_menu_list",
        "status": "review",
        "condition": " ",
        "reference": "",
        "author": "@Tearran",
        "group": "",
        "commands": "",
        "port": "",
        "arch": ""
    },
    {
        "id": "GEN048",
        "feature": "generate_jobs_from_json",
        "helpers": "",
        "description": "Generate jobs from JSON file. (generate_jobs_from_json)",
        "command": "generate_jobs_from_json",
        "options": "generate_jobs_from_json",
        "status": "review",
        "condition": " ",
        "reference": "",
        "author": "@Tearran",
        "group": "",
        "commands": "",
        "port": "",
        "arch": ""
    },
    {
        "id": "MOD049",
        "feature": "module_radarr",
        "helpers": "",
        "description": "Install radarr container (module_radarr)",
        "command": "module_radarr",
        "options": "install remove purge status help",
        "status": "Active",
        "condition": " ",
        "reference": "",
        "author": "@armbian",
        "group": "Downloaders",
        "commands": "",
        "port": "7878",
        "arch": "x86-64 arm64"
    },
    {
        "id": "TOG050",
        "feature": "toggle_ipv6",
        "helpers": "",
        "description": "Toggle IPv6 on or off (toggle_ipv6)",
        "command": "toggle_ipv6",
        "options": "toggle_ipv6",
        "status": "review",
        "condition": " ",
        "reference": "",
        "author": "@Tearran",
        "group": "",
        "commands": "",
        "port": "",
        "arch": ""
    },
    {
        "id": "ABO051",
        "feature": "about_armbian_configng",
        "helpers": "",
        "description": "Show general information about this tool (about_armbian_configng)",
        "command": "about_armbian_configng",
        "options": "about_armbian_configng",
        "status": "Active",
        "condition": " ",
        "reference": "",
        "author": "@igorpecovnik",
        "group": "",
        "commands": "",
        "port": "",
        "arch": ""
    },
    {
        "id": "MOD052",
        "feature": "module_qbittorrent",
        "helpers": "",
        "description": "Install qbittorrent container (module_qbittorrent)",
        "command": "module_qbittorrent",
        "options": "install remove purge status help",
        "status": "Active",
        "condition": " ",
        "reference": "",
        "author": "@qbittorrent",
        "group": "Downloaders",
        "commands": "",
        "port": "8090 6881",
        "arch": "x86-64 arm64"
    },
    {
        "id": "GEN053",
        "feature": "generate_json",
        "helpers": "",
        "description": " (generate_json)",
        "command": "generate_json",
        "options": "",
        "status": "",
        "condition": " ",
        "reference": "",
        "author": "",
        "group": "",
        "commands": "",
        "port": "",
        "arch": ""
    },
    {
        "id": "MOD054",
        "feature": "module_transmission",
        "helpers": "",
        "description": "Install transmission container (module_transmission)",
        "command": "module_transmission",
        "options": "install remove purge status help",
        "status": "Active",
        "condition": " ",
        "reference": "",
        "author": "@armbian",
        "group": "Downloaders",
        "commands": "",
        "port": "9091 51413",
        "arch": "x86-64 arm64"
    },
    {
        "id": "MOD055",
        "feature": "module_nextcloud",
        "helpers": "",
        "description": "Install nextcloud container (module_nextcloud)",
        "command": "module_nextcloud",
        "options": "install remove purge status help",
        "status": "Active",
        "condition": " ",
        "reference": "",
        "author": "",
        "group": "",
        "commands": "",
        "port": "443",
        "arch": "x86-64,arm64"
    },
    {
        "id": "SER056",
        "feature": "service",
        "helpers": "",
        "description": "Wrapper for service manipulation (service)",
        "command": "service",
        "options": "service install some.service",
        "status": "active",
        "condition": " ",
        "reference": "",
        "author": "@dimitry-ishenko",
        "group": "",
        "commands": "",
        "port": "",
        "arch": ""
    },
    {
        "id": "MOD057",
        "feature": "module_openhab",
        "helpers": "",
        "description": "Install Openhab (module_openhab)",
        "command": "module_openhab",
        "options": "install remove purge status help",
        "status": "Active",
        "condition": " ",
        "reference": "",
        "author": "@igorpecovnik",
        "group": "HomeAutomation",
        "commands": "",
        "port": "8080",
        "arch": "x86-64 arm64 armhf"
    },
    {
        "id": "SEE058",
        "feature": "see_menu",
        "helpers": "",
        "description": "Uses Avalible (Whiptail, DIALOG, READ) for the menu interface (see_menu)",
        "command": "see_menu",
        "options": "<function_name>",
        "status": "review",
        "condition": " ",
        "reference": "",
        "author": "Tearran",
        "group": "",
        "commands": "",
        "port": "",
        "arch": ""
    },
    {
        "id": "NET059",
        "feature": "network_config",
        "helpers": "",
        "description": "Netplan wrapper (network_config)",
        "command": "network_config",
        "options": "network_config",
        "status": "review",
        "condition": " ",
        "reference": "",
        "author": "@igorpecovnik",
        "group": "",
        "commands": "",
        "port": "",
        "arch": ""
    },
    {
        "id": "MOD060",
        "feature": "module_medusa",
        "helpers": "",
        "description": "Install medusa container (module_medusa)",
        "command": "module_medusa",
        "options": "install remove purge status help",
        "status": "Active",
        "condition": " ",
        "reference": "",
        "author": "@armbian",
        "group": "Downloaders",
        "commands": "",
        "port": "8081",
        "arch": "x86-64 arm64"
    },
    {
        "id": "MOD061",
        "feature": "module_syncthing",
        "helpers": "",
        "description": "Install syncthing container (module_syncthing)",
        "command": "module_syncthing",
        "options": "install remove purge status help",
        "status": "Active",
        "condition": " ",
        "reference": "",
        "author": "",
        "group": "",
        "commands": "",
        "port": "8884",
        "arch": "x86-64,arm64"
    },
    {
        "id": "ODR062",
        "feature": "Odroid board",
        "helpers": "",
        "description": " (Odroid board)",
        "command": "Odroid board",
        "options": "",
        "status": "",
        "condition": " ",
        "reference": "",
        "author": "",
        "group": "",
        "commands": "",
        "port": "",
        "arch": ""
    },
    {
        "id": "MOD063",
        "feature": "module_owncloud",
        "helpers": "",
        "description": "Install owncloud container (module_owncloud)",
        "command": "module_owncloud",
        "options": "install remove purge status help",
        "status": "Active",
        "condition": " ",
        "reference": "",
        "author": "@armbian",
        "group": "",
        "commands": "",
        "port": "7787",
        "arch": "x86-64,arm64"
    },
    {
        "id": "MOD064",
        "feature": "module_netdata",
        "helpers": "",
        "description": "Install netdata container (module_netdata)",
        "command": "module_netdata",
        "options": "install remove purge status help",
        "status": "Active",
        "condition": " ",
        "reference": "",
        "author": "@armbian",
        "group": "",
        "commands": "",
        "port": "19999",
        "arch": "x86-64,arm64"
    },
    {
        "id": "SET065",
        "feature": "set_colors",
        "helpers": "",
        "description": "Change the background color of the terminal or dialog box (set_colors)",
        "command": "set_colors",
        "options": "set_colors 0-7",
        "status": "Active",
        "condition": " ",
        "reference": "",
        "author": "@Tearran",
        "group": "",
        "commands": "",
        "port": "",
        "arch": ""
    },
    {
        "id": "ABO066",
        "feature": "about_armbian_configng",
        "helpers": "",
        "description": "Show general information about this tool (about_armbian_configng)",
        "command": "about_armbian_configng",
        "options": "about_armbian_configng",
        "status": "Active",
        "condition": " ",
        "reference": "",
        "author": "@igorpecovnik",
        "group": "",
        "commands": "",
        "port": "",
        "arch": ""
    },
    {
        "id": "SER067",
        "feature": "serve_doc",
        "helpers": "",
        "description": "Serve the edit and debug server. (serve_doc)",
        "command": "serve_doc",
        "options": "serve_doc",
        "status": "active",
        "condition": " ",
        "reference": "",
        "author": "@Tearran",
        "group": "",
        "commands": "",
        "port": "",
        "arch": ""
    },
    {
        "id": "UPD068",
        "feature": "update_json_data",
        "helpers": "",
        "description": "Update JSON data with system information (update_json_data)",
        "command": "update_json_data",
        "options": "update_json_data",
        "status": "review",
        "condition": " ",
        "reference": "",
        "author": "@Tearran",
        "group": "",
        "commands": "",
        "port": "",
        "arch": ""
    },
    {
        "id": "MOD069",
        "feature": "module_nfs",
        "helpers": "",
        "description": "Install nfs client (module_nfs)",
        "command": "module_nfs",
        "options": "install remove servers help",
        "status": "Active",
        "condition": " ",
        "reference": "",
        "author": "@igorpecovnik",
        "group": "",
        "commands": "",
        "port": "",
        "arch": ""
    },
    {
        "id": "SHO070",
        "feature": "show_infobox",
        "helpers": "",
        "description": "pipeline strings to an infobox  (show_infobox)",
        "command": "show_infobox",
        "options": "show_infobox <<< 'hello world' ; ",
        "status": "Active",
        "condition": " ",
        "reference": "",
        "author": "@Tearran",
        "group": "",
        "commands": "",
        "port": "",
        "arch": ""
    },
    {
        "id": "MOD071",
        "feature": "module_readarr",
        "helpers": "",
        "description": "Install readarr container (module_readarr)",
        "command": "module_readarr",
        "options": "install remove purge status help",
        "status": "Active",
        "condition": " ",
        "reference": "",
        "author": "@armbian",
        "group": "Downloaders",
        "commands": "",
        "port": "8787",
        "arch": "x86-64 arm64"
    },
    {
        "id": "MOD072",
        "feature": "module_uptimekuma",
        "helpers": "",
        "description": "Install uptimekuma container (module_uptimekuma)",
        "command": "module_uptimekuma",
        "options": "install remove purge status help",
        "status": "Active",
        "condition": " ",
        "reference": "",
        "author": "@armbian",
        "group": "",
        "commands": "",
        "port": "3001",
        "arch": "x86-64,arm64"
    },
    {
        "id": "DEF073",
        "feature": "default_wireless_network_config",
        "helpers": "",
        "description": "Stop hostapd, clean config (default_wireless_network_config)",
        "command": "default_wireless_network_config",
        "options": "default_wireless_network_config",
        "status": "review",
        "condition": " ",
        "reference": "",
        "author": "@igorpecovnik",
        "group": "",
        "commands": "",
        "port": "",
        "arch": ""
    },
    {
        "id": "UPD074",
        "feature": "update_sub_submenu_data",
        "helpers": "",
        "description": "Update sub-submenu descriptions based on conditions (update_sub_submenu_data)",
        "command": "update_sub_submenu_data",
        "options": "MenuID SubID SubSubID CMD",
        "status": "",
        "condition": " ",
        "reference": "",
        "author": "@Tearran",
        "group": "",
        "commands": "",
        "port": "",
        "arch": ""
    },
    {
        "id": "PAR075",
        "feature": "parse_menu_items",
        "helpers": "",
        "description": "Parse json to get list of desired menu or submenu items (parse_menu_items)",
        "command": "parse_menu_items",
        "options": "parse_menu_items 'menu_options_array'",
        "status": "Active",
        "condition": " ",
        "reference": "",
        "author": "@viraniac",
        "group": "",
        "commands": "",
        "port": "",
        "arch": ""
    },
    {
        "id": "SEE076",
        "feature": "see_use",
        "helpers": "",
        "description": "Show the usage of the functions. (see_use)",
        "command": "see_use",
        "options": "see_use",
        "status": "review",
        "condition": " ",
        "reference": "",
        "author": "@Tearran",
        "group": "",
        "commands": "",
        "port": "",
        "arch": ""
    },
    {
        "id": "MAN077",
        "feature": "manage_desktops",
        "helpers": "",
        "description": "Install Desktop environment (manage_desktops)",
        "command": "manage_desktops",
        "options": "manage_desktops xfce install",
        "status": "Active",
        "condition": " ",
        "reference": "",
        "author": "@igorpecovnik",
        "group": "",
        "commands": "",
        "port": "",
        "arch": ""
    },
    {
        "id": "MAN078",
        "feature": "manage_zsh",
        "helpers": "",
        "description": "Set system shell to BASH (manage_zsh)",
        "command": "manage_zsh",
        "options": "manage_zsh enable|disable",
        "status": "Active",
        "condition": " ",
        "reference": "",
        "author": "@igorpecovnik",
        "group": "",
        "commands": "",
        "port": "",
        "arch": ""
    },
    {
        "id": "MOD079",
        "feature": "module_sabnzbd",
        "helpers": "",
        "description": "Install sabnzbd container (module_sabnzbd)",
        "command": "module_sabnzbd",
        "options": "install remove purge status help",
        "status": "Active",
        "condition": " ",
        "reference": "",
        "author": "@armbian",
        "group": "Downloaders",
        "commands": "",
        "port": "8080",
        "arch": "x86-64 arm64"
    },
    {
        "id": "PKG080",
        "feature": "pkg_configure",
        "helpers": "",
        "description": "Configure an unconfigured package (pkg_configure)",
        "command": "pkg_configure",
        "options": "pkg_configure",
        "status": "Interface",
        "condition": " ",
        "reference": "",
        "author": "@dimitry-ishenko",
        "group": "",
        "commands": "",
        "port": "",
        "arch": ""
    },
    {
        "id": "SEE081",
        "feature": "see_cmd_list",
        "helpers": "",
        "description": "Generate a Help message for cli commands. (see_cmd_list)",
        "command": "see_cmd_list",
        "options": "see_cmd_list [category]",
        "status": "review",
        "condition": " ",
        "reference": "",
        "author": "@Tearran",
        "group": "",
        "commands": "",
        "port": "",
        "arch": ""
    },
    {
        "id": "MOD082",
        "feature": "module_mariadb",
        "helpers": "",
        "description": "Install mariadb container (module_mariadb)",
        "command": "module_mariadb",
        "options": "install remove purge status help",
        "status": "Active",
        "condition": " ",
        "reference": "",
        "author": "",
        "group": "",
        "commands": "",
        "port": "3306",
        "arch": ""
    },
    {
        "id": "DEF083",
        "feature": "default_network_config",
        "helpers": "",
        "description": "Revert network config back to Armbian defaults (default_network_config)",
        "command": "default_network_config",
        "options": "default_network_config",
        "status": "review",
        "condition": " ",
        "reference": "",
        "author": "@igorpecovnik",
        "group": "",
        "commands": "",
        "port": "",
        "arch": ""
    },
    {
        "id": "CHE084",
        "feature": "check_os_status",
        "helpers": "",
        "description": "Check if the current OS is supported based on /etc/armbian-distribution-status (check_os_status)",
        "command": "check_os_status",
        "options": "help",
        "status": "Active",
        "condition": " ",
        "reference": "",
        "author": "@Tearran",
        "group": "",
        "commands": "",
        "port": "",
        "arch": ""
    },
    {
        "id": "MOD085",
        "feature": "module_prowlarr",
        "helpers": "",
        "description": "Install prowlarr container (module_prowlarr)",
        "command": "module_prowlarr",
        "options": "install remove status help",
        "status": "Active",
        "condition": " ",
        "reference": "",
        "author": "@armbian",
        "group": "",
        "commands": "",
        "port": "9696",
        "arch": "x86-64,arm64"
    },
    {
        "id": "MOD086",
        "feature": "module_nfsd",
        "helpers": "",
        "description": "Install nfsd server (module_nfsd)",
        "command": "module_nfsd",
        "options": "install remove manage add status clients servers help",
        "status": "Active",
        "condition": " ",
        "reference": "",
        "author": "@igorpecovnik",
        "group": "",
        "commands": "",
        "port": "",
        "arch": ""
    },
    {
        "id": "SEE087",
        "feature": "see_ping",
        "helpers": "",
        "description": "Check the internet connection with fallback DNS (see_ping)",
        "command": "see_ping",
        "options": "see_ping",
        "status": "review",
        "condition": " ",
        "reference": "https://github.com/Tearran/configng/blob/main/config.ng.functions.sh#632",
        "author": "@Tearran",
        "group": "",
        "commands": "",
        "port": "",
        "arch": ""
    },
    {
        "id": "INS088",
        "feature": "install_docker",
        "helpers": "",
        "description": " (install_docker)",
        "command": "install_docker",
        "options": "",
        "status": "",
        "condition": " ",
        "reference": "",
        "author": "",
        "group": "",
        "commands": "",
        "port": "",
        "arch": ""
    },
    {
        "id": "UPG089",
        "feature": "Upgrade upstream distribution release",
        "helpers": "",
        "description": " (Upgrade upstream distribution release)",
        "command": "Upgrade upstream distribution release",
        "options": "",
        "status": "",
        "condition": " ",
        "reference": "",
        "author": "",
        "group": "",
        "commands": "",
        "port": "",
        "arch": ""
    },
    {
        "id": "UPD090",
        "feature": "update_skel",
        "helpers": "",
        "description": "Update the /etc/skel files in users directories (update_skel)",
        "command": "update_skel",
        "options": "update_skel",
        "status": "Active",
        "condition": " ",
        "reference": "",
        "author": "@igorpecovnik",
        "group": "",
        "commands": "",
        "port": "",
        "arch": ""
    },
    {
        "id": "CHA091",
        "feature": "Change hostname",
        "helpers": "",
        "description": " (Change hostname)",
        "command": "Change hostname",
        "options": "",
        "status": "",
        "condition": " ",
        "reference": "",
        "author": "",
        "group": "",
        "commands": "",
        "port": "",
        "arch": ""
    },
    {
        "id": "PKG092",
        "feature": "pkg_update",
        "helpers": "",
        "description": "Update package repository (pkg_update)",
        "command": "pkg_update",
        "options": "pkg_update",
        "status": "Interface",
        "condition": " ",
        "reference": "",
        "author": "@dimitry-ishenko",
        "group": "",
        "commands": "",
        "port": "",
        "arch": ""
    },
    {
        "id": "GET093",
        "feature": "get_user_continue_secure",
        "helpers": "",
        "description": "Secure version of get_user_continue (get_user_continue_secure)",
        "command": "get_user_continue_secure",
        "options": "get_user_continue_secure 'Do you wish to continue?' process_input",
        "status": "Active",
        "condition": " ",
        "reference": "",
        "author": "@Tearran",
        "group": "",
        "commands": "",
        "port": "",
        "arch": ""
    },
    {
        "id": "INS094",
        "feature": "install_plexmediaserver",
        "helpers": "",
        "description": "Install plexmediaserver from repo using apt (install_plexmediaserver)",
        "command": "install_plexmediaserver",
        "options": "install_plexmediaserver",
        "status": "Active",
        "condition": " ",
        "reference": "",
        "author": "@schwar3kat",
        "group": "",
        "commands": "",
        "port": "",
        "arch": ""
    },
    {
        "id": "MOD095",
        "feature": "module_emby",
        "helpers": "",
        "description": "Install embyserver container (module_emby)",
        "command": "module_emby",
        "options": "install remove purge status help",
        "status": "Active",
        "condition": " ",
        "reference": "",
        "author": "@schwar3kat",
        "group": "Media",
        "commands": "",
        "port": "8096",
        "arch": "x86-64 arm64"
    }
]
